postmon.py
setup.cfg
setup.py
postmon.egg-info/PKG-INFO
postmon.egg-info/SOURCES.txt
postmon.egg-info/dependency_links.txt
postmon.egg-info/requires.txt
postmon.egg-info/top_level.txt