Metadata-Version: 1.1
Name: postmon
Version: 0.2
Summary: Postmon service wrapper
Home-page: http://github.com/PostmonAPI/postmon-python
Author: Iuri de Silvio
Author-email: iurisilvio@gmail.com
License: MIT
Platform: UNKNOWN
Classifier: Development Status :: 3 - Alpha
Classifier: Intended Audience :: Developers
Classifier: License :: OSI Approved :: MIT License
Classifier: Natural Language :: Portuguese (Brazilian)
Classifier: Operating System :: OS Independent
Classifier: Programming Language :: Python :: 2
Classifier: Programming Language :: Python :: 3
Classifier: Topic :: Software Development :: Libraries :: Python Modules
